saleor_postfinance_plugin/__init__.py
saleor_postfinance_plugin/plugin.py
saleor_postfinance_plugin-0.0.3.dist-info/LICENSE
saleor_postfinance_plugin-0.0.3.dist-info/METADATA
saleor_postfinance_plugin-0.0.3.dist-info/WHEEL
saleor_postfinance_plugin-0.0.3.dist-info/entry_points.txt
saleor_postfinance_plugin-0.0.3.dist-info/top_level.txt
saleor_postfinance_plugin-0.0.3.dist-info/RECORD
