Metadata-Version: 2.1
Name: saleor-postfinance-plugin
Version: 0.0.3
Summary: Saleor PostFinance gateway plugin.
Home-page: https://github.com/significa/saleor-postfinance-plugin
Author: Significa
License: MIT
Keywords: saleor,saleor-plugin,saleor-gateway,saleor-gateway-plugin
Platform: UNKNOWN
Classifier: Development Status :: 3 - Alpha
Classifier: Intended Audience :: Developers
Classifier: License :: OSI Approved :: MIT License
Classifier: Programming Language :: Python :: 3.9
License-File: LICENSE
Requires-Dist: postfinancecheckout ==3.1.1
